housing_price_pred/__init__.py
housing_price_pred/ingest_data.py
housing_price_pred/logger.py
housing_price_pred/main.py
housing_price_pred/main_1.py
housing_price_pred/score.py
housing_price_pred/train.py
housing_price_pred-0.0.3.dist-info/LICENSE
housing_price_pred-0.0.3.dist-info/METADATA
housing_price_pred-0.0.3.dist-info/WHEEL
housing_price_pred-0.0.3.dist-info/top_level.txt
housing_price_pred-0.0.3.dist-info/RECORD
