Metadata-Version: 2.1
Name: housing-price-pred
Version: 0.0.3
Summary: Housing Price Prediction
Home-page: https://github.com/sibashisc/mle-training/tree/fix/9/ml-workflow
Author: Sibashis Chakraborty
Author-email: sibashis.chakrab@tigeranalytics.com
License: UNKNOWN
Platform: UNKNOWN
Classifier: Programming Language :: Python :: 3
Classifier: License :: OSI Approved :: MIT License
Classifier: Operating System :: OS Independent
Requires-Python: >=3.6
License-File: LICENSE
